AkvoFormPrint/__init__.py
AkvoFormPrint/enums.py
AkvoFormPrint/models.py
AkvoFormPrint/utils.py
AkvoFormPrint/parsers/__init__.py
AkvoFormPrint/parsers/akvo_arf_parser.py
AkvoFormPrint/parsers/akvo_flow_parser.py
AkvoFormPrint/parsers/base_parser.py
AkvoFormPrint/parsers/default_parser.py
AkvoFormPrint/stylers/__init__.py
AkvoFormPrint/stylers/base_styler.py
AkvoFormPrint/stylers/weasyprint_styler.py
AkvoFormPrint/styles/default.css
AkvoFormPrint/templates/form_template.html
AkvoFormPrint/templates/macros/question_macros.html
akvoformprint-0.1.0a9.dist-info/licenses/LICENSE
akvoformprint-0.1.0a9.dist-info/METADATA
akvoformprint-0.1.0a9.dist-info/WHEEL
akvoformprint-0.1.0a9.dist-info/top_level.txt
akvoformprint-0.1.0a9.dist-info/RECORD
