Metadata-Version: 2.4
Name: AkvoFormPrint
Version: 0.1.0a9
Summary: Render modular forms into PDF or HTML using WeasyPrint with custom templates and styling
Home-page: https://github.com/akvo/akvo-form-print
Author: Akvo
Author-email: Akvo <tech.consultancy@akvo.org>
Maintainer: Wayan Galih Pratama
Maintainer-email: Wayan Galih Pratama <wgprtm@gmail.com>
License-Expression: AGPL-3.0-only
Project-URL: Homepage, https://github.com/akvo/akvo-form-print
Project-URL: Bug Tracker, https://github.com/akvo/akvo-form-print/issues
Project-URL: Organization, https://github.com/akvo
Keywords: form,pdf,html,weasyprint,akvo
Classifier: Development Status :: 3 - Alpha
Classifier: Intended Audience :: Developers
Classifier: Programming Language :: Python :: 3
Classifier: Programming Language :: Python :: 3.8
Classifier: Programming Language :: Python :: 3.9
Classifier: Programming Language :: Python :: 3.10
Classifier: Programming Language :: Python :: 3.11
Classifier: Topic :: Software Development :: Libraries :: Python Modules
Requires-Python: >=3.8
License-File: LICENSE
Requires-Dist: weasyprint>=60.1
Requires-Dist: jinja2>=3.1.3
Requires-Dist: pydantic>=2.0.0
Dynamic: author
Dynamic: home-page
Dynamic: license-file
Dynamic: maintainer
Dynamic: requires-python
